{
    "$schema": "http://json-schema.org/draft-07/schema",
    "$id": "subdatatype",
    "title": "GC_META_SUBDATATYPE",
    "description": "",
    "type": "object",
    "version": "1.0",
    "anyOf": [
        {"properties": {"datatype": {"$ref": "http://schema_service:5000/datatype", "type": "object", "properties": {"name": {"const": "physical"}}}, "name": {"const": "string"}, "simple_datatype": {"$ref": "http://schema_service:5000/simple_datatype", "type": "object", "properties": {"name": {"const": "string"}}}, "is_default": {"const": 1}, "position": {"const": 1}, "active": {"const": 1}}},
        {"properties": {"datatype": {"$ref": "http://schema_service:5000/datatype", "type": "object", "properties": {"name": {"const": "physical"}}}, "name": {"const": "integer"}, "simple_datatype": {"$ref": "http://schema_service:5000/simple_datatype", "type": "object", "properties": {"name": {"const": "integer"}}}, "is_default": {"const": 0}, "position": {"const": 2}, "active": {"const": 1}}},
        {"properties": {"datatype": {"$ref": "http://schema_service:5000/datatype", "type": "object", "properties": {"name": {"const": "physical"}}}, "name": {"const": "float"}, "simple_datatype": {"$ref": "http://schema_service:5000/simple_datatype", "type": "object", "properties": {"name": {"const": "float"}}}, "is_default": {"const": 0}, "position": {"const": 3}, "active": {"const": 1}}},
        {"properties": {"datatype": {"$ref": "http://schema_service:5000/datatype", "type": "object", "properties": {"name": {"const": "physical"}}}, "name": {"const": "date"}, "simple_datatype": {"$ref": "http://schema_service:5000/simple_datatype", "type": "object", "properties": {"name": {"const": "date"}}}, "is_default": {"const": 0}, "position": {"const": 4}, "active": {"const": 1}}},
        {"properties": {"datatype": {"$ref": "http://schema_service:5000/datatype", "type": "object", "properties": {"name": {"const": "physical"}}}, "name": {"const": "enumerator"}, "simple_datatype": {"$ref": "http://schema_service:5000/simple_datatype", "type": "object", "properties": {"name": {"const": "string"}}}, "is_default": {"const": 0}, "position": {"const": 5}, "active": {"const": 1}}},
        {"properties": {"datatype": {"$ref": "http://schema_service:5000/datatype", "type": "object", "properties": {"name": {"const": "physical"}}}, "name": {"const": "catalogue"}, "simple_datatype": {"$ref": "http://schema_service:5000/simple_datatype", "type": "object", "properties": {"name": {"const": "string"}}}, "is_default": {"const": 0}, "position": {"const": 6}, "active": {"const": 1}}},
        {"properties": {"datatype": {"$ref": "http://schema_service:5000/datatype", "type": "object", "properties": {"name": {"const": "logical"}}}, "name": {"const": "string"}, "simple_datatype": {"$ref": "http://schema_service:5000/simple_datatype", "type": "object", "properties": {"name": {"const": "string"}}}, "is_default": {"const": 1}, "position": {"const": 1}, "active": {"const": 1}}},
        {"properties": {"datatype": {"$ref": "http://schema_service:5000/datatype", "type": "object", "properties": {"name": {"const": "logical"}}}, "name": {"const": "integer"}, "simple_datatype": {"$ref": "http://schema_service:5000/simple_datatype", "type": "object", "properties": {"name": {"const": "integer"}}}, "is_default": {"const": 0}, "position": {"const": 2}, "active": {"const": 1}}},
        {"properties": {"datatype": {"$ref": "http://schema_service:5000/datatype", "type": "object", "properties": {"name": {"const": "logical"}}}, "name": {"const": "float"}, "simple_datatype": {"$ref": "http://schema_service:5000/simple_datatype", "type": "object", "properties": {"name": {"const": "float"}}}, "is_default": {"const": 0}, "position": {"const": 3}, "active": {"const": 1}}},
        {"properties": {"datatype": {"$ref": "http://schema_service:5000/datatype", "type": "object", "properties": {"name": {"const": "logical"}}}, "name": {"const": "method"}, "simple_datatype": {"$ref": "http://schema_service:5000/simple_datatype", "type": "object", "properties": {"name": {"const": "string"}}}, "is_default": {"const": 0}, "position": {"const": 4}, "active": {"const": 1}}},
        {"properties": {"datatype": {"$ref": "http://schema_service:5000/datatype", "type": "object", "properties": {"name": {"const": "logical"}}}, "name": {"const": "insert"}, "simple_datatype": {"$ref": "http://schema_service:5000/simple_datatype", "type": "object", "properties": {"name": {"const": "string"}}}, "is_default": {"const": 0}, "position": {"const": 5}, "active": {"const": 1}}},
        {"properties": {"datatype": {"$ref": "http://schema_service:5000/datatype", "type": "object", "properties": {"name": {"const": "logical"}}}, "name": {"const": "update"}, "simple_datatype": {"$ref": "http://schema_service:5000/simple_datatype", "type": "object", "properties": {"name": {"const": "string"}}}, "is_default": {"const": 0}, "position": {"const": 6}, "active": {"const": 1}}},
        {"properties": {"datatype": {"$ref": "http://schema_service:5000/datatype", "type": "object", "properties": {"name": {"const": "logical"}}}, "name": {"const": "delete"}, "simple_datatype": {"$ref": "http://schema_service:5000/simple_datatype", "type": "object", "properties": {"name": {"const": "string"}}}, "is_default": {"const": 0}, "position": {"const": 7}, "active": {"const": 1}}},
        {"properties": {"datatype": {"$ref": "http://schema_service:5000/datatype", "type": "object", "properties": {"name": {"const": "geometry"}}}, "name": {"const": "text"}, "simple_datatype": {"$ref": "http://schema_service:5000/simple_datatype", "type": "object", "properties": {"name": {"const": null}}}, "is_default": {"const": 0}, "position": {"const": 1}, "active": {"const": 1}}},
        {"properties": {"datatype": {"$ref": "http://schema_service:5000/datatype", "type": "object", "properties": {"name": {"const": "geometry"}}}, "name": {"const": "point"}, "simple_datatype": {"$ref": "http://schema_service:5000/simple_datatype", "type": "object", "properties": {"name": {"const": null}}}, "is_default": {"const": 1}, "position": {"const": 2}, "active": {"const": 1}}},
        {"properties": {"datatype": {"$ref": "http://schema_service:5000/datatype", "type": "object", "properties": {"name": {"const": "geometry"}}}, "name": {"const": "line"}, "simple_datatype": {"$ref": "http://schema_service:5000/simple_datatype", "type": "object", "properties": {"name": {"const": null}}}, "is_default": {"const": 0}, "position": {"const": 3}, "active": {"const": 1}}},
        {"properties": {"datatype": {"$ref": "http://schema_service:5000/datatype", "type": "object", "properties": {"name": {"const": "geometry"}}}, "name": {"const": "area"}, "simple_datatype": {"$ref": "http://schema_service:5000/simple_datatype", "type": "object", "properties": {"name": {"const": null}}}, "is_default": {"const": 0}, "position": {"const": 4}, "active": {"const": 1}}},
        {"properties": {"datatype": {"$ref": "http://schema_service:5000/datatype", "type": "object", "properties": {"name": {"const": "geometry"}}}, "name": {"const": "text_set"}, "simple_datatype": {"$ref": "http://schema_service:5000/simple_datatype", "type": "object", "properties": {"name": {"const": null}}}, "is_default": {"const": 0}, "position": {"const": 5}, "active": {"const": 1}}},
        {"properties": {"datatype": {"$ref": "http://schema_service:5000/datatype", "type": "object", "properties": {"name": {"const": "geometry"}}}, "name": {"const": "line_set"}, "simple_datatype": {"$ref": "http://schema_service:5000/simple_datatype", "type": "object", "properties": {"name": {"const": null}}}, "is_default": {"const": 0}, "position": {"const": 7}, "active": {"const": 1}}},
        {"properties": {"datatype": {"$ref": "http://schema_service:5000/datatype", "type": "object", "properties": {"name": {"const": "geometry"}}}, "name": {"const": "area_set"}, "simple_datatype": {"$ref": "http://schema_service:5000/simple_datatype", "type": "object", "properties": {"name": {"const": null}}}, "is_default": {"const": 0}, "position": {"const": 8}, "active": {"const": 1}}},
        {"properties": {"datatype": {"$ref": "http://schema_service:5000/datatype", "type": "object", "properties": {"name": {"const": "geometry"}}}, "name": {"const": "point_set"}, "simple_datatype": {"$ref": "http://schema_service:5000/simple_datatype", "type": "object", "properties": {"name": {"const": null}}}, "is_default": {"const": 0}, "position": {"const": 6}, "active": {"const": 1}}},
        {"properties": {"datatype": {"$ref": "http://schema_service:5000/datatype", "type": "object", "properties": {"name": {"const": "join"}}}, "name": {"const": "1_1"}, "simple_datatype": {"$ref": "http://schema_service:5000/simple_datatype", "type": "object", "properties": {"name": {"const": "string"}}}, "is_default": {"const": 0}, "position": {"const": 1}, "active": {"const": 1}}},
        {"properties": {"datatype": {"$ref": "http://schema_service:5000/datatype", "type": "object", "properties": {"name": {"const": "join"}}}, "name": {"const": "1_n"}, "simple_datatype": {"$ref": "http://schema_service:5000/simple_datatype", "type": "object", "properties": {"name": {"const": "string"}}}, "is_default": {"const": 1}, "position": {"const": 2}, "active": {"const": 1}}},
        {"properties": {"datatype": {"$ref": "http://schema_service:5000/datatype", "type": "object", "properties": {"name": {"const": "join"}}}, "name": {"const": "m_n"}, "simple_datatype": {"$ref": "http://schema_service:5000/simple_datatype", "type": "object", "properties": {"name": {"const": "string"}}}, "is_default": {"const": 0}, "position": {"const": 3}, "active": {"const": 1}}},
        {"properties": {"datatype": {"$ref": "http://schema_service:5000/datatype", "type": "object", "properties": {"name": {"const": "geometry"}}}, "name": {"const": "text_dataless"}, "simple_datatype": {"$ref": "http://schema_service:5000/simple_datatype", "type": "object", "properties": {"name": {"const": null}}}, "is_default": {"const": 0}, "position": {"const": 9}, "active": {"const": 1}}},
        {"properties": {"datatype": {"$ref": "http://schema_service:5000/datatype", "type": "object", "properties": {"name": {"const": "geometry"}}}, "name": {"const": "point_dataless"}, "simple_datatype": {"$ref": "http://schema_service:5000/simple_datatype", "type": "object", "properties": {"name": {"const": null}}}, "is_default": {"const": 0}, "position": {"const": 10}, "active": {"const": 1}}},
        {"properties": {"datatype": {"$ref": "http://schema_service:5000/datatype", "type": "object", "properties": {"name": {"const": "geometry"}}}, "name": {"const": "area_dataless"}, "simple_datatype": {"$ref": "http://schema_service:5000/simple_datatype", "type": "object", "properties": {"name": {"const": null}}}, "is_default": {"const": 0}, "position": {"const": 12}, "active": {"const": 1}}},
        {"properties": {"datatype": {"$ref": "http://schema_service:5000/datatype", "type": "object", "properties": {"name": {"const": "geometry"}}}, "name": {"const": "line_dataless"}, "simple_datatype": {"$ref": "http://schema_service:5000/simple_datatype", "type": "object", "properties": {"name": {"const": null}}}, "is_default": {"const": 0}, "position": {"const": 11}, "active": {"const": 1}}}
    ],
    "required": ["datatype", "name", "simple_datatype"]
}